<vbox width="100%" height="100%">
    <style>
        body {
            font-family: Arial, sans-serif;
            background-color: #2e2e2e;
            color: white;
            display: flex;
            align-items: center;
            justify-content: center;
            height: 100vh;
            margin: 0;
        }
        
        .tutorial-menu-container {
            background-color: #444;
            padding: 20px;
            border-radius: 10px;
            box-shadow: 0 2px 10px rgba(0, 0, 0, 0.5);
            width: 400px;
        }
        
        h1 {
            text-align: center;
            margin-bottom: 20px;
        }
        
        .tutorial-list {
            margin-bottom: 20px;
        }
        
        .tutorial-item {
            background-color: #555;
            padding: 15px;
            margin-bottom: 10px;
            border-radius: 5px;
        }
        
        .tutorial-item h2 {
            margin: 0;
        }
        
        .tutorial-item p {
            margin: 5px 0 10px;
        }
        
        button.start-button {
            background-color: #007bff;
            border: none;
            border-radius: 5px;
            color: white;
            padding: 10px;
            cursor: pointer;
            transition: background-color 0.3s;
        }
        
        button.start-button:hover {
            background-color: #0056b3;
        }
        
        button.back-button {
            width: 100%;
            padding: 10px;
            background-color: #dc3545;
            border: none;
            border-radius: 5px;
            color: white;
            cursor: pointer;
        }
        
        button.back-button:hover {
            background-color: #c82333;
        }
    </style>
    <box styleName="header" width="100%">
        <label width="100%" styleName="header-label" text="Single Play Menu"/>
    </box>

    <hbox styleName="container" width="100%" height="100%" continuous="true">
        <item-renderer  >
            <box styleName="tutorial-item" verticalAlign="top" height="190" width="288">
                <vbox width="100%">
                    <label id="tutorialHeader" styleName="lobby-name" width="100%"/>
                    <label id="tutorialDescription" styleName="lobby-status" width="100%"/>
                </vbox>
                <button width="100px" id="joinButton" text="Start tutorial" styleName="join-button" verticalAlign="bottom"/>
            </box>
        </item-renderer>
        <data>
            <item tutorialHeader="Tutorial 1: Game Basics" tutorialDescription="Learn the fundamental mechanics of the game, including controls and interface." />
            <item tutorialHeader="Tutorial 2: Resource Management" tutorialDescription="Understand how to gather resources and manage your economy effectively." />
            <item tutorialHeader="Tutorial 3: Building Structures" tutorialDescription="Learn how to build bases and upgrade your defenses and offense." />
            <item tutorialHeader="Tutorial 4: Combat Strategies" tutorialDescription="Master the art of warfare and learn different strategies to defeat your enemies." />
            <item tutorialHeader="Tutorial 4: Combat Strategies" tutorialDescription="Master the art of warfare and learn different strategies to defeat your enemies." />
            <item tutorialHeader="Tutorial 4: Combat Strategies" tutorialDescription="Master the art of warfare and learn different strategies to defeat your enemies." />
            <item tutorialHeader="Tutorial 4: Combat Strategies" tutorialDescription="Master the art of warfare and learn different strategies to defeat your enemies." />
        </data>
    </hbox>
</vbox>